pylint_sqlalchemy/__init__.py
pylint_sqlalchemy/_version.py
pylint_sqlalchemy/dml_no_argument.py
pylint_sqlalchemy/orm.py
pylint_sqlalchemy/plugin.py
pylint_sqlalchemy-0.3.0.dist-info/LICENSE
pylint_sqlalchemy-0.3.0.dist-info/METADATA
pylint_sqlalchemy-0.3.0.dist-info/WHEEL
pylint_sqlalchemy-0.3.0.dist-info/top_level.txt
pylint_sqlalchemy-0.3.0.dist-info/RECORD
