Metadata-Version: 2.1
Name: pylint-sqlalchemy
Version: 0.3.0
Summary: pylint plugin to fix incompatibility issues with sqlalchemy
Home-page: https://github.com/gwax/pylint-sqlalchemy
Author: George Leslie-Waksman
Author-email: waksman@gmail.com
License: MIT
Keywords: pylint,sqlalchemy,plugin
Platform: any
Classifier: Environment :: Console
Classifier: Intended Audience :: Developers
Classifier: License :: OSI Approved :: MIT License
Classifier: Operating System :: Unix
Classifier: Programming Language :: Python :: 3.8
Classifier: Programming Language :: Python :: 3.9
Classifier: Programming Language :: Python :: 3.10
Classifier: Programming Language :: Python :: 3.11
Classifier: Programming Language :: Python :: 3
Classifier: Topic :: Software Development :: Quality Assurance
License-File: LICENSE
